palos/Genome.py
palos/MPIwrapper.py
palos/ProcessOptions.py
palos/__init__.py
palos/gviz_api.py
palos/statistics.py
palos/utils.py
palos/algorithm/BinarySearchTree.py
palos/algorithm/PCA.py
palos/algorithm/PartitionGraphIntoCliques.py
palos/algorithm/RBTree.py
palos/algorithm/__init__.py
palos/algorithm/clique.py
palos/algorithm/graph.py
palos/algorithm/pca_module.py
palos/algorithm/roman.py
palos/db/GenomeDB.py
palos/db/SunsetDB.py
palos/db/SunsetDB_test.py
palos/db/TAIRGeneXML2GenomeDB.py
palos/db/TaxonomyDB.py
palos/db/__init__.py
palos/io/AbstractGenomeFileWalker.py
palos/io/AbstractMatrixFileWalker.py
palos/io/FastaFile.py
palos/io/HDF5MatrixFile.py
palos/io/MatrixFile.py
palos/io/YHPyTables.py
palos/io/__init__.py
palos/io/latex.py
palos/mapper/AbstractDBJob.py
palos/mapper/AbstractMapper.py
palos/mapper/AbstractSunsetMapper.py
palos/mapper/AbstractVCFMapper.py
palos/mapper/__init__.py
palos/ngs/AbstractAlignmentAndVCFWorkflow.py
palos/ngs/AbstractAlignmentWorkflow.py
palos/ngs/AbstractNGSWorkflow.py
palos/ngs/AbstractVCFWorkflow.py
palos/ngs/GenericVCFWorkflow.py
palos/ngs/MapReduceGenomeFileWorkflow.py
palos/ngs/TestMapReduceVCFWorkflow.py
palos/ngs/__init__.py
palos/ngs/io/AlignmentDepthIntervalFile.py
palos/ngs/io/BamFile.py
palos/ngs/io/VCFFile.py
palos/ngs/io/__init__.py
palos/pedigree/PlinkPedigreeFile.py
palos/pedigree/__init__.py
palos/pegasus/AbstractBioinfoWorkflow.py
palos/pegasus/AbstractWorkflow.py
palos/pegasus/__init__.py
palos/plot/AbstractPlot.py
palos/plot/__init__.py
palos/plot/colours.py
palos/plot/yh_matplotlib.py
palos/plot/yh_matplotlib_artists.py
palos/plot/yh_mayavi.py
palos/polymorphism/Association.py
palos/polymorphism/AssociationLandscape.py
palos/polymorphism/AssociationLocus.py
palos/polymorphism/AssociationPeak.py
palos/polymorphism/BeagleGenotypeFile.py
palos/polymorphism/BeagleLikelihoodFile.py
palos/polymorphism/CNV.py
palos/polymorphism/PolymorphismTableFile.py
palos/polymorphism/SNP.py
palos/polymorphism/TwoSNPData.py
Palos-0.1.37.dist-info/METADATA
Palos-0.1.37.dist-info/WHEEL
Palos-0.1.37.dist-info/top_level.txt
Palos-0.1.37.dist-info/RECORD
