Metadata-Version: 2.1
Name: Palos
Version: 0.1.37
Summary: Misc Python modules developed and used by the yfish group
Home-page: https://github.com/polyactis/pymodule
Author: Yu S. Huang
Author-email: polyactis@gmail.com
License: Apache2
Platform: UNKNOWN
Classifier: Intended Audience :: Developers
Classifier: Intended Audience :: Science/Research
Classifier: Operating System :: Unix
Classifier: Programming Language :: Python
Classifier: Programming Language :: Python :: 3
Classifier: Topic :: Scientific/Engineering
Classifier: Topic :: Utilities
Requires-Python: >=2.7
Requires-Dist: h5py
Requires-Dist: matplotlib
Requires-Dist: numpy
Requires-Dist: scipy
Requires-Dist: sqlalchemy
Requires-Dist: statsmodels
Requires-Dist: tables
Requires-Dist: future
Requires-Dist: future-fstrings
Requires-Dist: biopython
Requires-Dist: pegaflow
